ariadne_django/__init__.py
ariadne_django/apps.py
ariadne_django/auth/__init__.py
ariadne_django/auth/decorators/__init__.py
ariadne_django/auth/decorators/login_is_required.py
ariadne_django/auth/decorators/permission_is_required.py
ariadne_django/scalars/README.md
ariadne_django/scalars/__init__.py
ariadne_django/scalars/decimal.py
ariadne_django/scalars/isodate.py
ariadne_django/scalars/isodatetime.py
ariadne_django/scalars/isotime.py
ariadne_django/scalars/json.py
ariadne_django/scalars/timedelta.py
ariadne_django/scalars/uuid.py
ariadne_django/scalars/utils/__init__.py
ariadne_django/scalars/utils/parsers.py
ariadne_django/templates/ariadne_django/graphql_playground.html
ariadne_django/tests/__init__.py
ariadne_django/tests/graphql_query_test.py
ariadne_django/views/__init__.py
ariadne_django/views/async_graphql.py
ariadne_django/views/base.py
ariadne_django/views/graphql.py
ariadne_django-0.3.0.dist-info/LICENSE
ariadne_django-0.3.0.dist-info/METADATA
ariadne_django-0.3.0.dist-info/WHEEL
ariadne_django-0.3.0.dist-info/top_level.txt
ariadne_django-0.3.0.dist-info/RECORD
