Metadata-Version: 2.1
Name: ariadne-django
Version: 0.3.0
Summary: ariadne_django is a python library for integrating django with ariadne.
Home-page: https://github.com/reset-button/ariadne_django
Author: Lexria
Author-email: noreply@lexria.com
License: BSD
Platform: any
Classifier: Development Status :: 2 - Pre-Alpha
Classifier: Intended Audience :: Developers
Classifier: License :: OSI Approved :: BSD License
Classifier: Operating System :: OS Independent
Classifier: Programming Language :: Python
Classifier: Programming Language :: Python :: 3.6
Classifier: Programming Language :: Python :: 3.7
Classifier: Programming Language :: Python :: 3.8
Classifier: Topic :: Software Development :: Libraries :: Python Modules
License-File: LICENSE
